{
    "data":[
        {   
            "id":1,
            "index":"NIFTY",
            "date":"22FEB24",
            "nextDate":"29FEB24",
            "qty":50,
            "strikeDistance":50,
            "straddleSpread":2.5
        },
        {
            "id":2,
            "index":"BANKNIFTY",
            "date":"21FEB24",
            "nextDate":"29FEB24",
            "qty":15,
            "strikeDistance":100,
            "straddleSpread":5
        },
        {
            "id":3,
            "index":"FINNIFTY",
            "date":"13FEB24",
            "nextDate":"20FEB24",
            "qty":40,
            "strikeDistance":50,
            "straddleSpread":2.5
        },
        {
            "id":4,
            "index":"MIDCPNIFTY",
            "date":"19FEB24",
            "nextDate":"26FEB24",
            "qty":75,
            "strikeDistance":25,
            "straddleSpread":1.2
        },
        {
            "id":5,
            "index":"SENSEX",
            "date":"SENSEX24223",
            "nextDate":"SENSEX24301",
            "qty":10,
            "strikeDistance":100,
            "straddleSpread":5
        }
    ]
}